Metadata-Version: 2.1
Name: ClashOfClans.py
Version: 1.0
Summary: Library for creating ClashOfClans bots and scripts.
Home-page: https://github.com/xXxCLOTIxXx/ClashOfClans.py
Author: Xsarz
Author-email: xsarzy@gmail.com
License: MIT
Download-URL: https://github.com/xXxCLOTIxXx/ClashOfClans.py/archive/refs/heads/main.zip
Keywords: ClashOfClans,ClashOfClansApi,api,ClashOfClans-bot,supercell,python,python3,python3.x,xsarz,official
Platform: UNKNOWN
